visual_compare/__init__.py
visual_compare/doc/__init__.py
visual_compare/doc/match.py
visual_compare/doc/models.py
visual_compare/doc/pdf.py
visual_compare/doc/pdf_test.py
visual_compare/doc/visual.py
visual_compare/doc/image/__init__.py
visual_compare/doc/image/compare_image.py
visual_compare/doc/image/image.py
visual_compare/doc/image/ocr.py
visual_compare/tests/__init__.py
visual_compare/tests/conftest.py
visual_compare/tests/test_downloader.py
visual_compare/tests/test_image.py
visual_compare/tests/test_ocr.py
visual_compare/tests/test_paddle.py
visual_compare/tests/test_pdf.py
visual_compare/tests/test_torch.py
visual_compare/tests/test_visual.py
visual_compare/utils/__init__.py
visual_compare/utils/common.py
visual_compare/utils/downloader.py
visual_compare-1.0.2.3.dist-info/METADATA
visual_compare-1.0.2.3.dist-info/WHEEL
visual_compare-1.0.2.3.dist-info/top_level.txt
visual_compare-1.0.2.3.dist-info/RECORD
