Metadata-Version: 2.1
Name: visual-compare
Version: 1.0.2.3
Summary: Image and PDF Compare
Home-page: https://github.com/cuidingyong/visual-compare
Author: Dillon
Author-email: cuidingyong@yeah.net
License: MIT
Keywords: visual compare image pdf diff
Platform: UNKNOWN
Classifier: Development Status :: 4 - Beta
Classifier: Intended Audience :: Developers
Classifier: License :: OSI Approved :: MIT License
Classifier: Operating System :: OS Independent
Classifier: Programming Language :: Python
Classifier: Programming Language :: Python :: 3
Classifier: Programming Language :: Python :: 3 :: Only
Classifier: Programming Language :: Python :: 3.8
Classifier: Programming Language :: Python :: 3.9
Classifier: Programming Language :: Python :: 3.10
Requires-Dist: opencv-python-headless (~=4.7)
Requires-Dist: numpy (~=1.24.3)
Requires-Dist: imutils (~=0.5.4)
Requires-Dist: scikit-image (~=0.20)
Requires-Dist: pytesseract (~=0.3.10)
Requires-Dist: parsimonious (~=0.10)
Requires-Dist: PyMuPDF (~=1.22)
Requires-Dist: pyzbar (~=0.1.9)
Requires-Dist: pylibdmtx (~=0.1.10)
Requires-Dist: Wand (~=0.6.11)
Requires-Dist: pydantic (~=1.8.2)
Requires-Dist: deepdiff (~=6.3.0)
Requires-Dist: easyocr (~=1.6.2)
